README.md
setup.py
maia/__init__.py
maia/autoinstaller.py
maia/loadings.py
maia/photo.py
maia/switch.py
py_maia.egg-info/PKG-INFO
py_maia.egg-info/SOURCES.txt
py_maia.egg-info/dependency_links.txt
py_maia.egg-info/top_level.txt