Metadata-Version: 2.1
Name: py-maia
Version: 1.5
Summary: Let's code better
Home-page: https://github.com/Arorior/maia
Author: Arorior
License: MIT
Platform: UNKNOWN
